[
  {
    "datum": "Mo. 16.03.",
    "gerichte": [
      {
        "kategorie": "Seezeit-Teller",
        "name": "Provenzalisches Ragout | Spätzle",
        "allergene": [
          "Bio Rindfleisch",
          "Zucchini",
          "Aubergine",
          "25a",
          "25d",
          "28"
        ],
        "preise": "4,40 € Studierende | 5,90 € Mitarbeiter | 8,70 € Gäste"
      },
      {
        "kategorie": "KombinierBar",
        "name": "Brokkolinuggets mit Chili - Sour Cream",
        "allergene": [
          "25a",
          "25c",
          "28",
          "30",
          "31",
          "33",
          "25e"
        ],
        "preise": "2,20 € Studierende | 3,30 € Mitarbeiter | 4,40 € Gäste"
      },
      {
        "kategorie": "Sättigungsbeilage",
        "name": "würzige Backkartoffeln",
        "allergene": [],
        "preise": "0,90 € Studierende | 1,00 € Mitarbeiter | 1,30 € Gäste"
      },
      {
        "kategorie": "Gemüsebeilage",
        "name": "Karotten",
        "allergene": [],
        "preise": "0,90 € Studierende | 1,00 € Mitarbeiter | 1,30 € Gäste"
      },
      {
        "kategorie": "Salatbeilage",
        "name": "Blattsalat mit Kräuterdressing",
        "allergene": [
          "3",
          "34",
          "36"
        ],
        "preise": "0,90 € Studierende | 1,00 € Mitarbeiter | 1,30 € Gäste"
      },
      {
        "kategorie": "Salatbeilage",
        "name": "Rohkostsalat",
        "allergene": [
          "Karotte",
          "Apfel",
          "Sellerie",
          "3",
          "33",
          "36"
        ],
        "preise": "0,90 € Studierende | 1,00 € Mitarbeiter | 1,30 € Gäste"
      },
      {
        "kategorie": "Dessert",
        "name": "Haselnusspudding",
        "allergene": [
          "31",
          "32c"
        ],
        "preise": "0,90 € Studierende | 1,00 € Mitarbeiter | 1,30 € Gäste"
      }
    ]
  },
  {
    "datum": "Di. 17.03.",
    "gerichte": [
      {
        "kategorie": "Seezeit-Teller",
        "name": "Falafel mit Orientalische Bulgurpfanne und Kräuterdip dazu Salat oder Dessert",
        "allergene": [
          "Paprika",
          "Aubergine",
          "Karotte",
          "25a",
          "30"
        ],
        "preise": "4,40 € Studierende | 5,90 € Mitarbeiter | 8,70 € Gäste"
      },
      {
        "kategorie": "KombinierBar",
        "name": "Currywurst geschnitten mit Sauce",
        "allergene": [
          "2",
          "3"
        ],
        "preise": "2,40 € Studierende | 3,60 € Mitarbeiter | 4,90 € Gäste"
      },
      {
        "kategorie": "Sättigungsbeilage",
        "name": "Pommes frites",
        "allergene": [],
        "preise": "0,90 € Studierende | 1,00 € Mitarbeiter | 1,30 € Gäste"
      },
      {
        "kategorie": "Gemüsebeilage",
        "name": "Kaisergemüse",
        "allergene": [],
        "preise": "0,90 € Studierende | 1,00 € Mitarbeiter | 1,30 € Gäste"
      },
      {
        "kategorie": "Salatbeilage",
        "name": "Blattsalat mit Senfdressing",
        "allergene": [
          "3",
          "34",
          "36"
        ],
        "preise": "0,90 € Studierende | 1,00 € Mitarbeiter | 1,30 € Gäste"
      },
      {
        "kategorie": "Salatbeilage",
        "name": "Rohkostsalat",
        "allergene": [
          "Paprika",
          "Mais",
          "Zucchini",
          "3",
          "36"
        ],
        "preise": "0,90 € Studierende | 1,00 € Mitarbeiter | 1,30 € Gäste"
      },
      {
        "kategorie": "Dessert",
        "name": "Sojajoghurt mit Mangokompott",
        "allergene": [
          "30"
        ],
        "preise": "0,90 € Studierende | 1,00 € Mitarbeiter | 1,30 € Gäste"
      }
    ]
  },
  {
    "datum": "Mi. 18.03.",
    "gerichte": [
      {
        "kategorie": "Seezeit-Teller",
        "name": "Käsespätzle mit Schmelzzwiebeln dazu Salat oder Dessert",
        "allergene": [
          "25a",
          "25d",
          "28",
          "31"
        ],
        "preise": "4,40 € Studierende | 5,90 € Mitarbeiter | 8,70 € Gäste"
      },
      {
        "kategorie": "KombinierBar",
        "name": "Bio Cevapcici mit Ajvarsauce",
        "allergene": [
          "25a",
          "28",
          "31",
          "33",
          "34",
          "9"
        ],
        "preise": "2,40 € Studierende | 3,60 € Mitarbeiter | 4,90 € Gäste"
      },
      {
        "kategorie": "Sättigungsbeilage",
        "name": "Djuvec-Reis",
        "allergene": [
          "33",
          "34"
        ],
        "preise": "0,90 € Studierende | 1,00 € Mitarbeiter | 1,30 € Gäste"
      },
      {
        "kategorie": "Gemüsebeilage",
        "name": "grüne Bohnen",
        "allergene": [],
        "preise": "0,90 € Studierende | 1,00 € Mitarbeiter | 1,30 € Gäste"
      },
      {
        "kategorie": "Salatbeilage",
        "name": "Blattsalat mit Kräuterdressing",
        "allergene": [
          "3",
          "34",
          "36"
        ],
        "preise": "0,90 € Studierende | 1,00 € Mitarbeiter | 1,30 € Gäste"
      },
      {
        "kategorie": "Salatbeilage",
        "name": "Gurkensalat",
        "allergene": [
          "3",
          "36"
        ],
        "preise": "0,90 € Studierende | 1,00 € Mitarbeiter | 1,30 € Gäste"
      },
      {
        "kategorie": "Dessert",
        "name": "Pfirsichjoghurt",
        "allergene": [
          "1",
          "31"
        ],
        "preise": "0,90 € Studierende | 1,00 € Mitarbeiter | 1,30 € Gäste"
      }
    ]
  },
  {
    "datum": "Do. 19.03.",
    "gerichte": [
      {
        "kategorie": "Seezeit-Teller",
        "name": "Bio-Pasta mit Bio-Sonnenblumenhack Bolognese dazu Salat oder Dessert",
        "allergene": [
          "25a",
          "33",
          "34"
        ],
        "preise": "4,40 € Studierende | 5,90 € Mitarbeiter | 8,70 € Gäste"
      },
      {
        "kategorie": "KombinierBar",
        "name": "Alaska-Seelachsfilet mit Kräutersauce",
        "allergene": [
          "26",
          "8",
          "31",
          "33",
          "34"
        ],
        "preise": "2,40 € Studierende | 3,60 € Mitarbeiter | 4,90 € Gäste"
      },
      {
        "kategorie": "Sättigungsbeilage",
        "name": "Basmatireis",
        "allergene": [],
        "preise": "0,90 € Studierende | 1,00 € Mitarbeiter | 1,30 € Gäste"
      },
      {
        "kategorie": "Gemüsebeilage",
        "name": "Mischgemüse",
        "allergene": [
          "33",
          "34"
        ],
        "preise": "0,90 € Studierende | 1,00 € Mitarbeiter | 1,30 € Gäste"
      },
      {
        "kategorie": "Salatbeilage",
        "name": "Blattsalat mit Senfdressing",
        "allergene": [
          "3",
          "34",
          "36"
        ],
        "preise": "0,90 € Studierende | 1,00 € Mitarbeiter | 1,30 € Gäste"
      },
      {
        "kategorie": "Salatbeilage",
        "name": "Rohkostsalat",
        "allergene": [
          "Paprika",
          "Mais",
          "Zucchini",
          "3",
          "36"
        ],
        "preise": "0,90 € Studierende | 1,00 € Mitarbeiter | 1,30 € Gäste"
      },
      {
        "kategorie": "Dessert",
        "name": "Vanillequark",
        "allergene": [
          "1",
          "31"
        ],
        "preise": "0,90 € Studierende | 1,00 € Mitarbeiter | 1,30 € Gäste"
      }
    ]
  },
  {
    "datum": "Fr. 20.03.",
    "gerichte": [
      {
        "kategorie": "Seezeit-Teller",
        "name": "Cordon bleu vom Schwein mit Thymiansauce und Bratkartoffeln dazu Salat oder Dessert",
        "allergene": [
          "2",
          "3",
          "25a",
          "31",
          "33"
        ],
        "preise": "4,40 € Studierende | 5,90 € Mitarbeiter | 8,70 € Gäste"
      },
      {
        "kategorie": "KombinierBar",
        "name": "vier Gemüsemaultaschen mit Zwiebelsauce",
        "allergene": [
          "25a",
          "34"
        ],
        "preise": "2,20 € Studierende | 3,30 € Mitarbeiter | 4,40 € Gäste"
      },
      {
        "kategorie": "Sättigungsbeilage",
        "name": "Schupfnudeln",
        "allergene": [
          "25a"
        ],
        "preise": "0,90 € Studierende | 1,00 € Mitarbeiter | 1,30 € Gäste"
      },
      {
        "kategorie": "Gemüsebeilage",
        "name": "Mandelbrokkoli",
        "allergene": [
          "32a"
        ],
        "preise": "0,90 € Studierende | 1,00 € Mitarbeiter | 1,30 € Gäste"
      },
      {
        "kategorie": "Salatbeilage",
        "name": "Blattsalat mit Kräuterdressing",
        "allergene": [
          "3",
          "34",
          "36"
        ],
        "preise": "0,90 € Studierende | 1,00 € Mitarbeiter | 1,30 € Gäste"
      },
      {
        "kategorie": "Salatbeilage",
        "name": "bunter Bohnensalat",
        "allergene": [
          "9",
          "36"
        ],
        "preise": "0,90 € Studierende | 1,00 € Mitarbeiter | 1,30 € Gäste"
      },
      {
        "kategorie": "Dessert",
        "name": "Waldfruchtjoghurt",
        "allergene": [
          "31"
        ],
        "preise": "0,90 € Studierende | 1,00 € Mitarbeiter | 1,30 € Gäste"
      }
    ]
  },
  {
    "datum": "Mo. 23.03.",
    "gerichte": [
      {
        "kategorie": "Seezeit-Teller",
        "name": "Schwäbisches Linsengericht mit Geflügelwiener und Spätzle dazu Salat oder Dessert",
        "allergene": [
          "Lauch",
          "Karotte",
          "Sellerie",
          "3",
          "25a",
          "33",
          "34",
          "36",
          "2",
          "25d",
          "28"
        ],
        "preise": "4,40 € Studierende | 5,90 € Mitarbeiter | 8,70 € Gäste"
      },
      {
        "kategorie": "KombinierBar",
        "name": "Gebackene Frühlingsrolle mit Apfel-Ingwer-Chutney",
        "allergene": [
          "25a",
          "33",
          "3",
          "36"
        ],
        "preise": "2,20 € Studierende | 3,30 € Mitarbeiter | 4,40 € Gäste"
      },
      {
        "kategorie": "Sättigungsbeilage",
        "name": "Gemüse-Glasnudeln",
        "allergene": [
          "1",
          "2",
          "4",
          "25a",
          "30"
        ],
        "preise": "0,90 € Studierende | 1,00 € Mitarbeiter | 1,30 € Gäste"
      },
      {
        "kategorie": "Gemüsebeilage",
        "name": "Asiatisches Gemüse",
        "allergene": [
          "1",
          "2",
          "4",
          "25a",
          "30"
        ],
        "preise": "0,90 € Studierende | 1,00 € Mitarbeiter | 1,30 € Gäste"
      },
      {
        "kategorie": "Salatbeilage",
        "name": "Blattsalat mit Kräuter-Joghurt-Dressing",
        "allergene": [
          "3",
          "31",
          "36"
        ],
        "preise": "0,90 € Studierende | 1,00 € Mitarbeiter | 1,30 € Gäste"
      },
      {
        "kategorie": "Salatbeilage",
        "name": "Karottensalat",
        "allergene": [
          "3",
          "36"
        ],
        "preise": "0,90 € Studierende | 1,00 € Mitarbeiter | 1,30 € Gäste"
      },
      {
        "kategorie": "Dessert",
        "name": "Apfel-Zimt Quark",
        "allergene": [
          "3",
          "31"
        ],
        "preise": "0,90 € Studierende | 1,00 € Mitarbeiter | 1,30 € Gäste"
      }
    ]
  },
  {
    "datum": "Di. 24.03.",
    "gerichte": [
      {
        "kategorie": "Seezeit-Teller",
        "name": "Chicken Nuggets mit Sweet Chili Sauce und Pommes frites dazu Salat oder Dessert",
        "allergene": [
          "25a",
          "9"
        ],
        "preise": "4,40 € Studierende | 5,90 € Mitarbeiter | 8,70 € Gäste"
      },
      {
        "kategorie": "KombinierBar",
        "name": "Mediterrane Tomatenrolle mit Thymiansauce",
        "allergene": [
          "25a",
          "34",
          "33"
        ],
        "preise": "2,20 € Studierende | 3,30 € Mitarbeiter | 4,40 € Gäste"
      },
      {
        "kategorie": "Sättigungsbeilage",
        "name": "Pommes frites",
        "allergene": [],
        "preise": "0,90 € Studierende | 1,00 € Mitarbeiter | 1,30 € Gäste"
      },
      {
        "kategorie": "Gemüsebeilage",
        "name": "Ratatouille",
        "allergene": [
          "2"
        ],
        "preise": "0,90 € Studierende | 1,00 € Mitarbeiter | 1,30 € Gäste"
      },
      {
        "kategorie": "Salatbeilage",
        "name": "Blattsalat mit dunklem Balsamicodressing",
        "allergene": [
          "1",
          "34",
          "36"
        ],
        "preise": "0,90 € Studierende | 1,00 € Mitarbeiter | 1,30 € Gäste"
      },
      {
        "kategorie": "Salatbeilage",
        "name": "Rohkostsalat",
        "allergene": [
          "Karotten",
          "Zucchini",
          "Rettich",
          "3",
          "34",
          "36"
        ],
        "preise": "0,90 € Studierende | 1,00 € Mitarbeiter | 1,30 € Gäste"
      },
      {
        "kategorie": "Dessert",
        "name": "Naturjoghurt mit Himbeeren",
        "allergene": [
          "31"
        ],
        "preise": "0,90 € Studierende | 1,00 € Mitarbeiter | 1,30 € Gäste"
      }
    ]
  },
  {
    "datum": "Mi. 25.03.",
    "gerichte": [
      {
        "kategorie": "Seezeit-Teller",
        "name": "Chili con Carne mit Sauerrahm und Potato Wedges",
        "allergene": [
          "Bio Rindfleisch",
          "Mais",
          "Paprika",
          "31",
          "25a"
        ],
        "preise": "4,40 € Studierende | 5,90 € Mitarbeiter | 8,70 € Gäste"
      },
      {
        "kategorie": "KombinierBar",
        "name": "zwei Gemüsefrikadellen mit Bärlauchsauce",
        "allergene": [
          "25a",
          "28",
          "1",
          "8",
          "31",
          "33",
          "34"
        ],
        "preise": "2,20 € Studierende | 3,30 € Mitarbeiter | 4,40 € Gäste"
      },
      {
        "kategorie": "Sättigungsbeilage",
        "name": "Kartoffelpüree",
        "allergene": [
          "3",
          "31"
        ],
        "preise": "0,90 € Studierende | 1,00 € Mitarbeiter | 1,30 € Gäste"
      },
      {
        "kategorie": "Gemüsebeilage",
        "name": "Rahmspinat",
        "allergene": [
          "8",
          "31",
          "33",
          "34"
        ],
        "preise": "0,90 € Studierende | 1,00 € Mitarbeiter | 1,30 € Gäste"
      },
      {
        "kategorie": "Salatbeilage",
        "name": "Blattsalat mit Kräuter-Joghurt-Dressing",
        "allergene": [
          "3",
          "31",
          "36"
        ],
        "preise": "0,90 € Studierende | 1,00 € Mitarbeiter | 1,30 € Gäste"
      },
      {
        "kategorie": "Salatbeilage",
        "name": "Rohkoststalat",
        "allergene": [
          "Gurke",
          "Kidneybohnen",
          "Mais",
          "3",
          "34",
          "36"
        ],
        "preise": "0,90 € Studierende | 1,00 € Mitarbeiter | 1,30 € Gäste"
      },
      {
        "kategorie": "Dessert",
        "name": "Rote Grütze mit Vanillesauce",
        "allergene": [
          "25e"
        ],
        "preise": "0,90 € Studierende | 1,00 € Mitarbeiter | 1,30 € Gäste"
      }
    ]
  },
  {
    "datum": "Do. 26.03.",
    "gerichte": [
      {
        "kategorie": "Seezeit-Teller",
        "name": "Blumenkohlcurry mit Cashewkernen und Basmatireis dazu Salat oder Dessert",
        "allergene": [
          "8",
          "25e",
          "32g"
        ],
        "preise": "4,40 € Studierende | 5,90 € Mitarbeiter | 8,70 € Gäste"
      },
      {
        "kategorie": "Salatbeilage",
        "name": "Blattsalat mit dunklem Balsamicodressing",
        "allergene": [
          "1",
          "34",
          "36"
        ],
        "preise": "0,90 € Studierende | 1,00 € Mitarbeiter | 1,30 € Gäste"
      },
      {
        "kategorie": "Salatbeilage",
        "name": "Farmersalat",
        "allergene": [
          "Weißkohl",
          "Karotte",
          "Joghurt",
          "31",
          "34"
        ],
        "preise": "0,90 € Studierende | 1,00 € Mitarbeiter | 1,30 € Gäste"
      },
      {
        "kategorie": "Dessert",
        "name": "Pudding mit Vanillegeschmack",
        "allergene": [
          "31"
        ],
        "preise": "0,90 € Studierende | 1,00 € Mitarbeiter | 1,30 € Gäste"
      }
    ]
  },
  {
    "datum": "Fr. 27.03.",
    "gerichte": [
      {
        "kategorie": "Seezeit-Teller",
        "name": "Cannelloni überbacken mit Ricotta-Spinatfüllung und Tomatensauce dazu Salat oder Dessert",
        "allergene": [
          "25a",
          "28",
          "31",
          "33"
        ],
        "preise": "4,40 € Studierende | 5,90 € Mitarbeiter | 8,70 € Gäste"
      },
      {
        "kategorie": "Salatbeilage",
        "name": "Blattsalat mit Kräuter-Joghurt-Dressing",
        "allergene": [
          "3",
          "31",
          "36"
        ],
        "preise": "0,90 € Studierende | 1,00 € Mitarbeiter | 1,30 € Gäste"
      },
      {
        "kategorie": "Salatbeilage",
        "name": "Rohkoststalat",
        "allergene": [
          "Gurke",
          "Kidneybohnen",
          "Mais",
          "3",
          "34",
          "36"
        ],
        "preise": "0,90 € Studierende | 1,00 € Mitarbeiter | 1,30 € Gäste"
      },
      {
        "kategorie": "Dessert",
        "name": "Mousse au chocolat",
        "allergene": [
          "30",
          "31",
          "32c"
        ],
        "preise": "0,90 € Studierende | 1,00 € Mitarbeiter | 1,30 € Gäste"
      }
    ]
  }
]